db_backup_runner/__init__.py
db_backup_runner/cli.py
db_backup_runner/manager.py
db_backup_runner/types.py
db_backup_runner/utils.py
db_backup_runner/custom/__init__.py
db_backup_runner/custom/provider/__init__.py
db_backup_runner/custom/provider/_custom.py
db_backup_runner/provider/__init__.py
db_backup_runner/provider/_base.py
db_backup_runner/provider/_mariadb.py
db_backup_runner/provider/_mysql.py
db_backup_runner/provider/_postgres.py
db_backup_runner/provider/_redis.py
db_backup_runner-0.1.3.dist-info/METADATA
db_backup_runner-0.1.3.dist-info/WHEEL
db_backup_runner-0.1.3.dist-info/entry_points.txt
db_backup_runner-0.1.3.dist-info/licenses/LICENSE
db_backup_runner-0.1.3.dist-info/RECORD
