Metadata-Version: 2.4
Name: db-backup-runner
Version: 0.1.3
Summary: Run any db backups (and others) from inside its own docker container
Project-URL: Repository, https://github.com/burgdev/db-backup-runner
Project-URL: Documentation, https://burgdev.github.io/db-backup-runner/
Project-URL: Changelog, https://github.com/burgdev/db-backup-runner/blob/main/CHANGELOG.md
Project-URL: Releases, https://github.com/burgdev/db-backup-runner/releases
License-File: LICENSE
Classifier: Development Status :: 4 - Beta
Classifier: Intended Audience :: Developers
Classifier: License :: OSI Approved :: MIT License
Classifier: Programming Language :: Python :: 3.12
Requires-Python: >=3.12
Requires-Dist: click>=8.1.7
Requires-Dist: docker>=7.1.0
Requires-Dist: loguru>=0.7.3
Requires-Dist: python-cron
Requires-Dist: python-dotenv>=1.0.1
Requires-Dist: requests>=2.32.3
Requires-Dist: tqdm>=4.67.1
